robot_net/__init__.py
robot_net/lark.py
robot_net/lark_bitable.py
robot_net/lark_robot.py
robot_net/lark_sheets.py
robot_net/lark_sheets_data.py
robot_net/utils.py
robot_net-0.3.0.dist-info/METADATA
robot_net-0.3.0.dist-info/WHEEL
robot_net-0.3.0.dist-info/RECORD
