Metadata-Version: 2.4
Name: robot_net
Version: 0.3.0
Summary: robot network tools
Author: mance
Classifier: License :: OSI Approved :: MIT License
Classifier: Operating System :: OS Independent
Classifier: Programming Language :: Python :: 3
Requires-Python: >=3.11
Requires-Dist: requests
Requires-Dist: requests-toolbelt
